{
  "id": "buying-selling-organs",
  "sourceUrl": "https://dorar.net/feqhia/4356",
  "titleTh": "การซื้อขายอวัยวะมนุษย์",
  "titleAr": "بيع الأعضاء البشرية",
  "categoryId": "muamalat",
  "subcategoryId": "muamalat-buyu",
  "summaryTh": "ญุมฮูรนักวิชาการห้ามการซื้อขายอวัยวะมนุษย์เด็ดขาด เพราะร่างกายมนุษย์ไม่ใช่ทรัพย์สิน บางนักวิชาการสมัยใหม่อนุญาตการบริจาค (ไม่ขาย) อวัยวะของผู้เสียชีวิตเมื่อมีความจำเป็นทางการแพทย์",
  "introduction": "การซื้อขายอวัยวะมนุษย์ (بيع الأعضاء البشرية) เป็นประเด็นที่เกิดขึ้นในยุคสมัยใหม่ ฟิกฮ์คลาสสิกไม่ได้กล่าวถึงโดยตรง แต่มีหลักการที่เกี่ยวข้อง นักวิชาการต้องตอบคำถามว่า: ร่างกายมนุษย์เป็นทรัพย์สินที่ขายได้หรือไม่ และการบริจาคอวัยวะต่างจากการขายหรือไม่",
  "keywords": [
    "อวัยวะ",
    "การปลูกถ่ายอวัยวะ",
    "บริจาคอวัยวะ",
    "ร่างกายมนุษย์",
    "بيع الأعضاء",
    "زرع الأعضاء",
    "التبرع بالأعضاء"
  ],
  "opinions": [
    {
      "id": "organ-selling-haram",
      "position": "ห้ามการซื้อขายอวัยวะอย่างเด็ดขาด (ญุมฮูร)",
      "positionAr": "بيع الأعضاء البشرية محرم بالإجماع",
      "scholars": [
        {
          "name": "สภาฟิกฮ์อิสลามนานาชาติ (OIC)",
          "nameAr": "مجمع الفقه الإسلامي الدولي",
          "era": "มติที่ 26 ปี 1988",
          "madhab": "consensus",
          "type": "fiqh_council"
        },
        {
          "name": "สภาอุละมาอ์อาวุโสแห่งซาอุดีอาระเบีย",
          "nameAr": "هيئة كبار العلماء",
          "era": "ฟัตวาร่วมสมัย",
          "madhab": "hanbali",
          "type": "fiqh_council"
        },
        {
          "name": "อิบนุ บาซ",
          "nameAr": "ابن باز",
          "era": "1330-1420 ฮ.ศ.",
          "madhab": "hanbali",
          "type": "contemporary_scholar"
        }
      ],
      "evidence": [
        {
          "type": "hadith",
          "textAr": "إِنَّ اللَّهَ حَرَّمَ أَشْيَاءَ فَلَا تَعْتَدُوهَا، وَفَرَضَ فَرَائِضَ فَلَا تُضَيِّعُوهَا، وَحَدَّ حُدُودًا فَلَا تَعْتَدُوهَا، وَسَكَتَ عَنْ أَشْيَاءَ رَحْمَةً مِنْهُ غَيْرَ نِسْيَانٍ فَلَا تَبْحَثُوا عَنْهَا",
          "translationTh": "อัลลอฮฺทรงห้ามสิ่งหนึ่งๆ อย่าละเมิด ทรงบัญญัติหน้าที่ต่างๆ อย่าทอดทิ้ง ทรงกำหนดขอบเขตอย่าล่วงเกิน และทรงเงียบเกี่ยวกับสิ่งหนึ่งๆ เป็นความเมตตาจากพระองค์ ไม่ใช่ลืม อย่าสืบค้น",
          "hadithCollection": "สุนันอัด-ดาเราะกุฏนีย์",
          "narrator": "อบู ษะอฺละบะฮฺ (ร.อ.)",
          "grading": "หะซัน",
          "references": [
            {
              "bookTh": "ดุรอรอัด-ดีนียะฮฺ — หมวดบีอ์",
              "bookAr": "الدرر السنية",
              "url": "https://dorar.net/feqhia/4356"
            }
          ]
        },
        {
          "type": "quran",
          "textAr": "وَلَقَدْ كَرَّمْنَا بَنِي آدَمَ",
          "translationTh": "และแท้จริงเราได้ให้เกียรติแก่บนีอาดัม",
          "surah": "อัล-อิสรออ์",
          "ayah": "17:70",
          "references": [
            {
              "bookTh": "อัลกุรอาน สูเราะฮฺอัล-อิสรออ์ อายะฮฺที่ 70",
              "bookAr": "سورة الإسراء آية 70",
              "url": "https://quran.com/17/70"
            }
          ]
        }
      ],
      "explanation": "ญุมฮูรห้ามการซื้อขายอวัยวะเพราะ:\n1. ร่างกายมนุษย์ได้รับเกียรติจากอัลลอฮฺ ไม่ใช่ทรัพย์สินที่ขายได้\n2. มนุษย์เป็น 'ผู้ดูแล' (أمانة) ไม่ใช่ 'เจ้าของ' ร่างกายของตัวเอง\n3. การขายอวัยวะเปิดประตูสู่การขูดรีดคนจน\n4. สภาฟิกฮ์ OIC มีมติในปี 1988 ว่าห้ามอย่างชัดเจน"
    },
    {
      "id": "organ-donation-permissible",
      "position": "การบริจาค (ไม่ขาย) อวัยวะหลังเสียชีวิตอนุญาตเมื่อจำเป็น (บางนักวิชาการสมัยใหม่)",
      "positionAr": "يجوز التبرع بالأعضاء بعد الموت للضرورة الطبية",
      "scholars": [
        {
          "name": "ยูสุฟ อัล-เกาะเราะฎอวีย์",
          "nameAr": "يوسف القرضاوي",
          "era": "1345-1443 ฮ.ศ.",
          "madhab": "independent",
          "type": "contemporary_scholar"
        },
        {
          "name": "สภาฟิกฮ์ยุโรป (ECFR)",
          "nameAr": "المجلس الأوروبي للإفتاء والبحوث",
          "era": "ก่อตั้ง 1997",
          "madhab": "independent",
          "type": "fiqh_council"
        }
      ],
      "evidence": [
        {
          "type": "hadith",
          "textAr": "مَنْ نَفَّسَ عَنْ مُؤْمِنٍ كُرْبَةً مِنْ كُرَبِ الدُّنْيَا نَفَّسَ اللَّهُ عَنْهُ كُرْبَةً مِنْ كُرَبِ يَوْمِ الْقِيَامَةِ",
          "translationTh": "ผู้ใดที่บรรเทาความทุกข์ยากชนิดหนึ่งของผู้ศรัทธา อัลลอฮฺจะทรงบรรเทาความทุกข์ยากของเขาในวันกิยามะฮฺ",
          "hadithCollection": "เศาะฮีหฺมุสลิม",
          "hadithNumber": 2699,
          "narrator": "อบู ฮุร็อยเราะฮฺ (ร.อ.)",
          "grading": "เศาะฮีหฺ",
          "references": [
            {
              "bookTh": "เศาะฮีหฺมุสลิม",
              "bookAr": "صحيح مسلم",
              "author": "อิมามมุสลิม",
              "url": "https://sunnah.com/muslim:2699"
            }
          ]
        }
      ],
      "explanation": "ทัศนะนี้แยกระหว่าง 'การขาย' กับ 'การบริจาค':\n- การขายอวัยวะ: ฮะรอมอย่างเด็ดขาด (เอกฉันท์)\n- การบริจาคอวัยวะหลังเสียชีวิตโดยสมัครใจ: อนุญาตในกรณีที่ผู้รับต้องการเพื่อรักษาชีวิต\n\nเงื่อนไข:\n1. ต้องบริจาค ไม่ใช่ขาย\n2. ต้องได้รับความยินยอมล่วงหน้าหรือจากทายาท\n3. ต้องมีความจำเป็นทางการแพทย์จริงๆ\n4. ไม่ทำให้เกิดอันตรายต่อผู้บริจาคที่ยังมีชีวิต"
    }
  ],
  "relatedFatwaIds": ["intellectual-property-rights", "peer-to-peer-lending"],
  "lastUpdated": "2026-03-10"
}
