{
  "id": "dropshipping-types",
  "sourceUrl": "https://dorar.net/feqhia/4356",
  "titleTh": "ดร็อปชิปปิ้ง: รูปแบบที่ฮะลาลและฮะรอม",
  "titleAr": "البيع بالعمولة والدروبشيبينج",
  "categoryId": "muamalat",
  "subcategoryId": "muamalat-buyu",
  "summaryTh": "ดร็อปชิปปิ้งมีหลายรูปแบบ บางรูปแบบฮะลาล บางรูปแบบฮะรอม ขึ้นอยู่กับโครงสร้างสัญญา นักวิชาการส่วนใหญ่สมัยใหม่อนุญาตรูปแบบที่เป็นนายหน้า (وكالة) แต่ห้ามรูปแบบที่ขายสิ่งที่ยังไม่มีในครอบครอง",
  "introduction": "ดร็อปชิปปิ้ง (Dropshipping) คือรูปแบบธุรกิจที่ผู้ขายรับออเดอร์จากลูกค้า แล้วสั่งซื้อสินค้าจากซัพพลายเออร์โดยตรงให้ส่งถึงลูกค้า โดยผู้ขายไม่ต้องสต็อกสินค้าเอง ปัญหาชะรีอะฮฺคือ: ผู้ขายกำลังขายสิ่งที่ยังไม่มีในครอบครอง (بيع ما لا تملك)",
  "keywords": [
    "ดร็อปชิปปิ้ง",
    "ขายออนไลน์",
    "อีคอมเมิร์ซ",
    "นายหน้า",
    "الدروبشيبينج",
    "البيع بالعمولة",
    "بيع ما لا يملك"
  ],
  "opinions": [
    {
      "id": "dropshipping-wakala-permissible",
      "position": "อนุญาตถ้าเป็นรูปแบบนายหน้า (วะกาละฮฺ) (ส่วนใหญ่สมัยใหม่)",
      "positionAr": "يجوز الدروبشيبينج بصيغة الوكالة",
      "scholars": [
        {
          "name": "สภาฟิกฮ์อิสลามนานาชาติ (OIC)",
          "nameAr": "مجمع الفقه الإسلامي الدولي",
          "era": "ฟัตวาสมัยใหม่",
          "madhab": "consensus",
          "type": "fiqh_council"
        },
        {
          "name": "ยูสุฟ อัล-เกาะเราะฎอวีย์",
          "nameAr": "يوسف القرضاوي",
          "era": "1345-1443 ฮ.ศ.",
          "madhab": "independent",
          "type": "contemporary_scholar"
        }
      ],
      "evidence": [
        {
          "type": "hadith",
          "textAr": "إِنَّمَا الْبَيْعُ عَنْ تَرَاضٍ",
          "translationTh": "การซื้อขายนั้น (สมบูรณ์) เมื่อมีความยินยอมร่วมกัน",
          "hadithCollection": "สุนันอิบนุ มาญะฮฺ",
          "hadithNumber": 2185,
          "narrator": "อบู สะอีด อัล-ค็อดรีย์ (ร.อ.)",
          "grading": "เศาะฮีหฺ",
          "references": [
            {
              "bookTh": "สุนันอิบนุ มาญะฮฺ",
              "bookAr": "سنن ابن ماجه",
              "author": "อิบนุ มาญะฮฺ",
              "url": "https://sunnah.com/ibnmajah:2185"
            }
          ]
        }
      ],
      "explanation": "รูปแบบที่อนุญาตคือ:\n1. วะกาละฮฺ (Agency): ผู้ขายบอกลูกค้าชัดเจนว่าเป็นตัวแทน รับค่าคอมมิชชัน ไม่ใช่กำไรจากการขายเอง\n2. ซะลัม: รับเงินลูกค้าล่วงหน้าทั้งหมดก่อนสั่งซัพพลายเออร์ โดยมีเงื่อนไขครบ\n3. อิสติศนาอ์: สั่งผลิตสินค้าเฉพาะตามสเปก\n\nรูปแบบเหล่านี้ไม่เข้าข่ายการขายสิ่งที่ยังไม่ได้ครอบครอง"
    },
    {
      "id": "dropshipping-haram-selling-unowned",
      "position": "ห้ามถ้าขายสิ่งที่ยังไม่มีหรือไม่ได้ครอบครอง (บางนักวิชาการ)",
      "positionAr": "لا يجوز الدروبشيبينج إذا اشتمل على بيع ما لا يملكه",
      "scholars": [
        {
          "name": "อิบนุ อุษัยมีน",
          "nameAr": "ابن عثيمين",
          "era": "1347-1421 ฮ.ศ.",
          "madhab": "hanbali",
          "type": "contemporary_scholar"
        },
        {
          "name": "บางนักวิชาการซาอุดีอาระเบีย",
          "nameAr": "بعض العلماء السعوديين",
          "era": "ปัจจุบัน",
          "madhab": "hanbali",
          "type": "contemporary_scholar"
        }
      ],
      "evidence": [
        {
          "type": "hadith",
          "textAr": "لَا تَبِعْ مَا لَيْسَ عِنْدَكَ",
          "translationTh": "จงอย่าขายสิ่งที่ไม่อยู่กับเจ้า",
          "hadithCollection": "สุนันอัต-ติรมิซีย์",
          "hadithNumber": 1232,
          "narrator": "หะกีม อิบนุ หิซาม (ร.อ.)",
          "grading": "เศาะฮีหฺ",
          "references": [
            {
              "bookTh": "สุนันอัต-ติรมิซีย์",
              "bookAr": "سنن الترمذي",
              "author": "อิมามอัต-ติรมิซีย์",
              "url": "https://sunnah.com/tirmidhi:1232"
            }
          ]
        }
      ],
      "explanation": "หะดีษห้ามขายสิ่งที่ไม่มีในครอบครองโดยตรง รูปแบบดร็อปชิปปิ้งที่ฮะรอมคือ:\n1. ลงประกาศขายสินค้า รับชำระเงิน แล้วค่อยสั่งซื้อจากซัพพลายเออร์\n2. กำหนดราคาเองโดยที่ยังไม่ได้ซื้อสินค้ามาก่อน\n3. รับความเสี่ยงในฐานะผู้ขายโดยตรง ไม่ใช่นายหน้า\n\nในรูปแบบนี้ ณ ขณะขาย ผู้ขายยังไม่ได้เป็นเจ้าของสินค้า ซึ่งขัดหะดีษโดยตรง"
    },
    {
      "id": "dropshipping-depends-on-structure",
      "position": "ขึ้นอยู่กับโครงสร้างสัญญา (ทัศนะสมัยใหม่ที่ยืดหยุ่น)",
      "positionAr": "يتوقف الحكم على هيكل العقد",
      "scholars": [
        {
          "name": "มุหัมมัด ตะกีย์ อุษมานีย์",
          "nameAr": "محمد تقي العثماني",
          "era": "ปัจจุบัน",
          "madhab": "hanafi",
          "type": "contemporary_scholar"
        }
      ],
      "evidence": [
        {
          "type": "quran",
          "textAr": "يَا أَيُّهَا الَّذِينَ آمَنُوا أَوْفُوا بِالْعُقُودِ",
          "translationTh": "โอ้บรรดาผู้ศรัทธา! จงปฏิบัติตามพันธสัญญา",
          "surah": "อัล-มาอิดะฮฺ",
          "ayah": "5:1",
          "references": [
            {
              "bookTh": "อัลกุรอาน สูเราะฮฺอัล-มาอิดะฮฺ อายะฮฺที่ 1",
              "bookAr": "سورة المائدة آية 1",
              "url": "https://quran.com/5/1"
            }
          ]
        }
      ],
      "explanation": "ทัศนะนี้เน้นว่าหุก่มขึ้นกับโครงสร้างสัญญา:\n- ถ้าผู้ขายเป็นนายหน้า (وكيل) และลูกค้ารู้ว่ากำลังซื้อจากซัพพลายเออร์ — อนุญาต\n- ถ้าผู้ขายซื้อจากซัพพลายเออร์ก่อน แล้วค่อยขายต่อ แม้ส่งตรงจากซัพพลายเออร์ — อนุญาต เพราะครอบครองโดยชะรีอะฮฺแล้ว\n- ถ้าขายโดยไม่ได้เป็นเจ้าของหรือนายหน้า — ฮะรอม"
    }
  ],
  "relatedFatwaIds": ["affiliate-marketing-ruling", "salam-advance-payment", "electronic-contract-validity"],
  "lastUpdated": "2026-03-10"
}
