{
  "id": "fasting-monday-thursday",
  "sourceUrl": "https://dorar.net/feqhia/2857",
  "titleTh": "การถือศีลอดวันจันทร์และพฤหัสบดี — สุนนะฮฺมุอักกะดะฮฺ",
  "titleAr": "صيام الاثنين والخميس",
  "categoryId": "sawm",
  "subcategoryId": "sawm-sunnah",
  "summaryTh": "นักวิชาการทั้งหมดเห็นพ้องว่าการถือศีลอดวันจันทร์และพฤหัสบดีเป็นสุนนะฮฺมุอักกะดะฮฺ (สุนนะฮฺที่เน้นย้ำ) เพราะท่านนะบีย์ ﷺ ทรงถือศีลอดสองวันนี้สม่ำเสมอ และทรงอธิบายว่าเป็นวันที่การกระทำของมนุษย์ถูกนำเสนอต่ออัลลอฮฺ",
  "introduction": "ท่านนะบีย์ ﷺ ทรงถือศีลอดวันจันทร์และพฤหัสบดีเป็นประจำและทรงอธิบายเหตุผล การถือศีลอดสองวันนี้จึงเป็นสุนนะฮฺที่ชัดเจนและนักวิชาการไม่มีข้อขัดแย้งในหุก่มพื้นฐาน",
  "keywords": [
    "ถือศีลอดวันจันทร์",
    "ถือศีลอดวันพฤหัส",
    "สุนนะฮฺมุอักกะดะฮฺ",
    "การงานถูกนำเสนอ",
    "صيام الاثنين",
    "صيام الخميس",
    "السنة",
    "الصيام"
  ],
  "opinions": [
    {
      "id": "monday-thursday-sunnah",
      "position": "การถือศีลอดวันจันทร์และพฤหัสบดีเป็นสุนนะฮฺมุอักกะดะฮฺ",
      "positionAr": "صيام الاثنين والخميس سنة مؤكدة",
      "scholars": [
        {
          "name": "อิมามอบู หะนีฟะฮฺ",
          "nameAr": "الإمام أبو حنيفة",
          "era": "80-150 ฮ.ศ.",
          "madhab": "hanafi",
          "type": "madhab_founder"
        },
        {
          "name": "อิมามมาลิก",
          "nameAr": "الإمام مالك",
          "era": "93-179 ฮ.ศ.",
          "madhab": "maliki",
          "type": "madhab_founder"
        },
        {
          "name": "อิมามอัช-ชาฟิอีย์",
          "nameAr": "الإمام الشافعي",
          "era": "150-204 ฮ.ศ.",
          "madhab": "shafii",
          "type": "madhab_founder"
        },
        {
          "name": "อิมามอะหฺมัด อิบนุ หัมบัล",
          "nameAr": "الإمام أحمد بن حنبل",
          "era": "164-241 ฮ.ศ.",
          "madhab": "hanbali",
          "type": "madhab_founder"
        }
      ],
      "evidence": [
        {
          "type": "hadith",
          "textAr": "تُعْرَضُ الأَعْمَالُ يَوْمَ الاِثْنَيْنِ وَالْخَمِيسِ، فَأُحِبُّ أَنْ يُعْرَضَ عَمَلِي وَأَنَا صَائِمٌ",
          "translationTh": "การงานต่างๆ จะถูกนำเสนอ (ต่ออัลลอฮฺ) ในวันจันทร์และวันพฤหัสบดี ฉันชอบที่การงานของฉันจะถูกนำเสนอในขณะที่ฉันกำลังถือศีลอด",
          "hadithCollection": "ติรมิซีย์",
          "hadithNumber": 747,
          "narrator": "อบู ฮุร็อยเราะฮฺ",
          "grading": "หะซัน เศาะฮีหฺ",
          "references": [
            {
              "bookTh": "ญามิอฺ อัต-ติรมิซีย์",
              "bookAr": "جامع الترمذي",
              "author": "อิมามอัต-ติรมิซีย์",
              "url": "https://sunnah.com/tirmidhi:747"
            }
          ]
        },
        {
          "type": "hadith",
          "textAr": "كَانَ رَسُولُ اللَّهِ صَلَّى اللَّهُ عَلَيْهِ وَسَلَّمَ يَصُومُ الاِثْنَيْنِ وَالْخَمِيسَ",
          "translationTh": "ท่านนะบีย์ ﷺ ทรงถือศีลอดวันจันทร์และวันพฤหัสบดี",
          "hadithCollection": "มุสลิม",
          "hadithNumber": 1162,
          "narrator": "อาอิชะฮฺ",
          "grading": "เศาะฮีหฺ",
          "references": [
            {
              "bookTh": "เศาะฮีหฺ มุสลิม",
              "bookAr": "صحيح مسلم",
              "author": "อิมามมุสลิม",
              "url": "https://sunnah.com/muslim:1162"
            }
          ]
        }
      ],
      "explanation": "ท่านนะบีย์ ﷺ ทรงถือศีลอดสองวันนี้สม่ำเสมอและทรงอธิบายเหตุผลคือเป็นวันที่การกระทำถูกนำเสนอต่ออัลลอฮฺ นักวิชาการจึงเห็นพ้องกันว่าเป็นสุนนะฮฺที่ควรปฏิบัติตาม ไม่มีข้อขัดแย้งในหุก่มนี้"
    }
  ],
  "relatedFatwaIds": ["fasting-six-shawwal", "fasting-arafah", "fasting-ashura"],
  "lastUpdated": "2026-03-10"
}
