{
  "id": "fasting-suppository",
  "sourceUrl": "https://dorar.net/feqhia/2754",
  "titleTh": "การใช้ยาเหน็บทวารหนักขณะถือศีลอด",
  "titleAr": "التحاميل (اللبوس) والصيام",
  "categoryId": "sawm",
  "subcategoryId": "sawm-muftiraat",
  "summaryTh": "นักวิชาการร่วมสมัยส่วนใหญ่ รวมถึงสภานิติศาสตร์อิสลามสากล เห็นว่าการใช้ยาเหน็บทวารหนัก (Suppository) ไม่ทำให้เสียศีลอด เพราะไม่ใช่การกินดื่มและไม่ได้อยู่ในความหมายของการกินดื่ม",
  "introduction": "ยาเหน็บทวารหนัก (Suppository) เป็นรูปแบบยาที่ใช้สอดเข้าทางทวารหนักเพื่อรักษาอาการต่างๆ เช่น ลดไข้ แก้ปวด หรือรักษาอาการท้องผูก นักวิชาการมีความเห็นแตกต่างกันว่าทำให้เสียศีลอดหรือไม่",
  "keywords": [
    "ยาเหน็บ",
    "ทวารหนัก",
    "ถือศีลอด",
    "التحاميل",
    "اللبوس",
    "الصيام"
  ],
  "opinions": [
    {
      "id": "no-break",
      "position": "ยาเหน็บทวารหนักไม่ทำให้เสียศีลอด",
      "positionAr": "التحاميل الشرجية لا تفطر الصائم",
      "scholars": [
        {
          "name": "สภานิติศาสตร์อิสลามสากล",
          "nameAr": "مجمع الفقه الإسلامي الدولي",
          "era": "ก่อตั้ง 1401 ฮ.ศ.",
          "madhab": "independent",
          "type": "fiqh_council"
        },
        {
          "name": "อิบนุ ตัยมียะฮฺ",
          "nameAr": "ابن تيمية",
          "era": "661-728 ฮ.ศ.",
          "madhab": "hanbali",
          "type": "classical_scholar"
        },
        {
          "name": "อิบนุ หัซม์",
          "nameAr": "ابن حزم",
          "era": "384-456 ฮ.ศ.",
          "madhab": "dhahiri",
          "type": "classical_scholar"
        }
      ],
      "evidence": [
        {
          "type": "scholarly_reasoning",
          "textAr": "التحاميل ليست أكلاً ولا شرباً ولا في معناهما، والدبر ليس منفذاً معتاداً للطعام والشراب",
          "translationTh": "ยาเหน็บไม่ใช่การกินหรือดื่ม และไม่ได้อยู่ในความหมายของการกินดื่ม และทวารหนักไม่ใช่ช่องทางปกติของอาหารและเครื่องดื่ม",
          "source": "สภานิติศาสตร์อิสลามสากล",
          "references": [
            {
              "bookTh": "สารานุกรมฟิกฮ์ - หมวดยาเหน็บ",
              "bookAr": "الموسوعة الفقهية - التحاميل",
              "url": "https://dorar.net/feqhia/2754"
            }
          ]
        },
        {
          "type": "scholarly_reasoning",
          "textAr": "قال ابن تيمية: الحقنة لا تفطر لأنها ليست أكلاً ولا شرباً ولا بمعنى الأكل والشرب",
          "translationTh": "อิบนุ ตัยมียะฮฺกล่าวว่า: ยาสวนทวารไม่ทำให้เสียศีลอด เพราะไม่ใช่การกินหรือดื่ม และไม่ได้อยู่ในความหมายของการกินดื่ม",
          "source": "อิบนุ ตัยมียะฮฺ",
          "references": [
            {
              "bookTh": "อิสลามเว็บ - ฟัตวาเรื่องยาเหน็บขณะถือศีลอด",
              "bookAr": "إسلام ويب - فتوى التحاميل والصيام",
              "url": "https://www.islamweb.net/ar/fatwa/56875/"
            }
          ]
        }
      ],
      "explanation": "ทัศนะนี้เป็นทัศนะที่อิบนุ ตัยมียะฮฺเลือก และเป็นมติของสภานิติศาสตร์อิสลามสากล โดยเห็นว่ายาเหน็บไม่มีสถานะเทียบเท่าการกินดื่ม เพราะทวารหนักไม่ใช่ช่องทางที่อาหารเข้าสู่ร่างกาย และยาเหน็บไม่ได้ให้สารอาหารแก่ร่างกาย\n\nอิบนุ หัซม์ (มัซฮับซอฮิรีย์) ก็เห็นว่าไม่ทำให้เสียศีลอด เพราะไม่มีตัวบทจากอัลกุรอานหรือหะดีษที่ระบุเรื่องนี้โดยตรง"
    },
    {
      "id": "break-classical",
      "position": "ยาเหน็บทวารหนักทำให้เสียศีลอด",
      "positionAr": "التحاميل الشرجية تفطر الصائم",
      "scholars": [
        {
          "name": "มัซฮับหะนะฟีย์",
          "nameAr": "الحنفية",
          "era": "",
          "madhab": "hanafi",
          "type": "madhab"
        },
        {
          "name": "มัซฮับมาลิกีย์",
          "nameAr": "المالكية",
          "era": "",
          "madhab": "maliki",
          "type": "madhab"
        },
        {
          "name": "มัซฮับชาฟิอีย์",
          "nameAr": "الشافعية",
          "era": "",
          "madhab": "shafii",
          "type": "madhab"
        },
        {
          "name": "มัซฮับหัมบะลีย์ (ทัศนะในตำรา)",
          "nameAr": "الحنابلة",
          "era": "",
          "madhab": "hanbali",
          "type": "madhab"
        }
      ],
      "evidence": [
        {
          "type": "scholarly_reasoning",
          "textAr": "كل ما وصل إلى الجوف من منفذ مفتوح أفسد الصوم",
          "translationTh": "ทุกสิ่งที่ถึงช่องท้องผ่านช่องทางที่เปิดอยู่ ทำให้ศีลอดเสีย",
          "source": "ทัศนะมัซฮับทั้งสี่ในตำราคลาสสิก",
          "references": [
            {
              "bookTh": "อิสลามเว็บ - ฟัตวาเรื่องยาสวนทวาร",
              "bookAr": "إسلام ويب - فتوى الحقنة الشرجية والصيام",
              "url": "https://www.islamweb.net/ar/fatwa/10686/"
            }
          ]
        }
      ],
      "explanation": "มัซฮับทั้งสี่ในตำราคลาสสิกเห็นว่าสิ่งที่เข้าสู่ร่างกายผ่านช่องทางเปิด (ทวารหนัก) ทำให้เสียศีลอด โดยใช้หลักกิยาส (การเทียบ) กับการกินดื่ม อย่างไรก็ตาม อิบนุ ตัยมียะฮฺวิพากษ์ว่าการเทียบนี้ไม่ถูกต้อง เพราะสิ่งที่ทำให้เสียศีลอดคือการกินดื่ม ไม่ใช่ทุกสิ่งที่เข้าสู่ร่างกาย"
    }
  ],
  "relatedFatwaIds": ["fasting-injection", "fasting-endoscopy"],
  "lastUpdated": "2026-03-10"
}