{
  "id": "forex-currency-trading",
  "sourceUrl": "https://dorar.net/feqhia/10345",
  "titleTh": "การซื้อขายเงินตราต่างประเทศ (ฟอเร็กซ์ / Forex)",
  "titleAr": "المتاجرة في العملات الأجنبية (الفوركس)",
  "categoryId": "muamalat",
  "subcategoryId": "islamic-finance",
  "summaryTh": "การแลกเปลี่ยนเงินตราต่างประเทศ (ศอรฺฟ์) อนุญาตโดยอิจมาอฺหากแลกทันที (يداً بيد) แต่ฟอเร็กซ์ออนไลน์สมัยใหม่มีปัญหาหลายประการ: margin trading ที่มีดอกเบี้ย (swap/rollover) การไม่ส่งมอบจริง (T+2) leverage สูง สภาฟิกฮ์และนักวิชาการส่วนใหญ่ห้ามฟอเร็กซ์ออนไลน์แบบ margin",
  "introduction": "ฟอเร็กซ์ (Forex / Foreign Exchange) คือตลาดซื้อขายแลกเปลี่ยนสกุลเงินต่างประเทศ ซึ่งเป็นตลาดการเงินที่ใหญ่ที่สุดในโลก มีมูลค่าการซื้อขายกว่า 6 ล้านล้านดอลลาร์ต่อวัน อิสลามอนุญาตการแลกเปลี่ยนเงินตรา (الصرف) ตามเงื่อนไขหะดีษริบา คือต้องรับส่งทันที (يداً بيد) และเท่ากันหากเป็นเงินชนิดเดียวกัน ปัญหาหลักของฟอเร็กซ์ออนไลน์คือ:\n\n1. Margin trading — ยืมเงินจากโบรกเกอร์ (leverage 1:100 ถึง 1:500)\n2. Swap/Rollover — ค่าธรรมเนียมค้างคืน (ริบา)\n3. ไม่มีการส่งมอบเงินตราจริง — เป็นเพียงการเดิมพันราคา\n4. T+2 Settlement — การชำระเงินล่าช้า 2 วันทำการ ไม่ใช่ทันที",
  "keywords": [
    "ฟอเร็กซ์",
    "แลกเปลี่ยนเงินตรา",
    "สกุลเงิน",
    "margin trading",
    "swap",
    "leverage",
    "ศอรฺฟ์",
    "Islamic account",
    "swap-free",
    "الفوركس",
    "الصرف",
    "تداول العملات",
    "الهامش",
    "الرافعة المالية"
  ],
  "opinions": [
    {
      "id": "forex-spot-permissible",
      "position": "การแลกเปลี่ยนเงินตราแบบสปอตอนุญาต (อิจมาอฺ) หากรับส่งทันที",
      "positionAr": "صرف العملات الفوري جائز بالإجماع بشرط التقابض",
      "scholars": [
        {
          "name": "อิมามอบูหะนีฟะฮฺ",
          "nameAr": "الإمام أبو حنيفة",
          "era": "80-150 ฮ.ศ.",
          "madhab": "hanafi",
          "type": "classical_scholar"
        },
        {
          "name": "อิมามมาลิก",
          "nameAr": "الإمام مالك",
          "era": "93-179 ฮ.ศ.",
          "madhab": "maliki",
          "type": "classical_scholar"
        },
        {
          "name": "อิมามอัช-ชาฟิอีย์",
          "nameAr": "الإمام الشافعي",
          "era": "150-204 ฮ.ศ.",
          "madhab": "shafii",
          "type": "classical_scholar"
        },
        {
          "name": "อิมามอะหฺมัด อิบนุ หัมบัล",
          "nameAr": "الإمام أحمد بن حنبل",
          "era": "164-241 ฮ.ศ.",
          "madhab": "hanbali",
          "type": "classical_scholar"
        }
      ],
      "evidence": [
        {
          "type": "hadith",
          "textAr": "الذَّهَبُ بِالذَّهَبِ، وَالْفِضَّةُ بِالْفِضَّةِ، وَالْبُرُّ بِالْبُرِّ، وَالشَّعِيرُ بِالشَّعِيرِ، وَالتَّمْرُ بِالتَّمْرِ، وَالْمِلْحُ بِالْمِلْحِ، مِثْلاً بِمِثْلٍ، سَوَاءً بِسَوَاءٍ، يَداً بِيَدٍ، فَإِذَا اخْتَلَفَتْ هَذِهِ الأَصْنَافُ فَبِيعُوا كَيْفَ شِئْتُمْ إِذَا كَانَ يَداً بِيَدٍ",
          "translationTh": "ทองกับทอง เงินกับเงิน ข้าวสาลีกับข้าวสาลี ข้าวบาร์เลย์กับข้าวบาร์เลย์ อินทผลัมกับอินทผลัม เกลือกับเกลือ เท่ากัน ต่อเท่ากัน มือต่อมือ และหากต่างชนิดก็ซื้อขายได้ตามที่ต้องการ โดยต้องมือต่อมือ (ทันที)",
          "hadithCollection": "เศาะฮีหฺมุสลิม",
          "hadithNumber": "1587a",
          "narrator": "อุบาดะฮฺ อิบนุ อัศ-ศอมิต (ร.อ.)",
          "grading": "เศาะฮีหฺ",
          "references": [
            {
              "bookTh": "เศาะฮีหฺมุสลิม",
              "bookAr": "صحيح مسلم",
              "author": "อิมามมุสลิม",
              "url": "https://sunnah.com/muslim:1587a"
            }
          ]
        },
        {
          "type": "hadith",
          "textAr": "لاَ تَبِيعُوا الذَّهَبَ بِالذَّهَبِ إِلاَّ مِثْلاً بِمِثْلٍ وَلاَ تُشِفُّوا بَعْضَهَا عَلَى بَعْضٍ وَلاَ تَبِيعُوا مِنْهَا غَائِبًا بِنَاجِزٍ",
          "translationTh": "จงอย่าขายทองกับทอง นอกจากเท่ากัน อย่าเพิ่มบางส่วนเหนือบางส่วน และอย่าขายสิ่งที่ไม่อยู่กับสิ่งที่อยู่ (ต้องส่งมอบทันที)",
          "hadithCollection": "เศาะฮีหฺ อัล-บุคอรีย์",
          "hadithNumber": 2177,
          "narrator": "อบูสะอีด อัล-ค็อดรีย์ (ร.อ.)",
          "grading": "เศาะฮีหฺ",
          "references": [
            {
              "bookTh": "เศาะฮีหฺ อัล-บุคอรีย์",
              "bookAr": "صحيح البخاري",
              "author": "อิมามอัล-บุคอรีย์",
              "url": "https://sunnah.com/bukhari:2177"
            }
          ]
        }
      ],
      "explanation": "นักวิชาการทุกมัซฮับเห็นพ้องกันว่าการแลกเปลี่ยนสกุลเงินต่างชนิดอนุญาตได้ หลักการมาจากหะดีษ 6 ชนิดริบาวีย์ (ทอง เงิน ข้าวสาลี ข้าวบาร์เลย์ อินทผลัม เกลือ) โดยนักวิชาการเทียบเงินตราสมัยใหม่กับทอง-เงิน:\n\n**เงื่อนไขการแลกเปลี่ยน:**\n- ถ้าชนิดเดียวกัน (เช่น บาทแลกบาท): ต้องเท่ากัน + ทันที\n- ถ้าต่างชนิด (เช่น บาทแลกดอลลาร์): จำนวนต่างกันได้ + แต่ต้องทันที (يداً بيد)\n\n**ตะกอบุฎ (การรับส่ง) สมัยใหม่:**\nสภาฟิกฮ์ยอมรับ 'ตะกอบุฎฮุกมีย์' (การรับมอบโดยหุก่ม) เช่น การโอนเข้าบัญชีทันที ไม่จำเป็นต้องรับเงินสดมือต่อมือจริง\n\nการแลกเงินที่ธนาคาร ร้าน Money Changer หรือ ATM ถือว่าอนุญาตเพราะรับส่งทันที"
    },
    {
      "id": "forex-online-margin-haram",
      "position": "ฟอเร็กซ์ออนไลน์แบบ margin ไม่อนุญาต (ทัศนะสภาฟิกฮ์และนักวิชาการส่วนใหญ่)",
      "positionAr": "تداول الفوركس عبر الإنترنت بالهامش محرم - قول المجامع والأكثرين",
      "scholars": [
        {
          "name": "สภาฟิกฮ์อิสลามนานาชาติ (OIC)",
          "nameAr": "مجمع الفقه الإسلامي الدولي",
          "era": "มติปี 2000",
          "madhab": null,
          "type": "contemporary_scholar"
        },
        {
          "name": "ลัจนะฮฺ อัด-ดาอิมะฮฺ ลิล-บุหูษ อัล-อิลมียะฮฺ",
          "nameAr": "اللجنة الدائمة للبحوث العلمية",
          "era": "ร่วมสมัย",
          "madhab": "hanbali",
          "type": "contemporary_scholar"
        },
        {
          "name": "อิบนุ บาซ",
          "nameAr": "ابن باز",
          "era": "1330-1420 ฮ.ศ.",
          "madhab": "hanbali",
          "type": "contemporary_scholar"
        },
        {
          "name": "ดร.อะลีย์ อัล-กอเราะฮฺดาฆีย์",
          "nameAr": "د. علي القره داغي",
          "era": "ร่วมสมัย",
          "madhab": null,
          "type": "contemporary_scholar"
        },
        {
          "name": "ดร.ยูซุฟ อัล-เกาะเราะฎอวีย์",
          "nameAr": "د. يوسف القرضاوي",
          "era": "1926-2022",
          "madhab": null,
          "type": "contemporary_scholar"
        }
      ],
      "evidence": [
        {
          "type": "quran",
          "textAr": "وَأَحَلَّ اللَّهُ الْبَيْعَ وَحَرَّمَ الرِّبَا",
          "translationTh": "อัลลอฮฺทรงอนุมัติการค้าขาย และทรงห้ามริบา",
          "surah": "อัล-บะเกาะเราะฮฺ",
          "ayah": "2:275",
          "references": [
            {
              "bookTh": "อัลกุรอาน สูเราะฮฺอัล-บะเกาะเราะฮฺ อายะฮฺที่ 275",
              "bookAr": "سورة البقرة آية 275",
              "url": "https://quran.com/2/275"
            }
          ]
        },
        {
          "type": "hadith",
          "textAr": "لَعَنَ رَسُولُ اللَّهِ صَلَّى اللَّهُ عَلَيْهِ وَسَلَّمَ آكِلَ الرِّبَا وَمُوكِلَهُ",
          "translationTh": "ท่านรอซูลุลลอฮฺ (ศ็อลลัลลอฮุอะลัยฮิวะซัลลัม) สาปแช่งผู้กินริบาและผู้ให้ริบา",
          "hadithCollection": "เศาะฮีหฺมุสลิม",
          "hadithNumber": 1598,
          "narrator": "ญาบิร (ร.อ.)",
          "grading": "เศาะฮีหฺ",
          "references": [
            {
              "bookTh": "เศาะฮีหฺมุสลิม",
              "bookAr": "صحيح مسلم",
              "author": "อิมามมุสลิม",
              "url": "https://sunnah.com/muslim:1598"
            }
          ]
        },
        {
          "type": "hadith",
          "textAr": "نَهَى رَسُولُ اللَّهِ صلى الله عليه وسلم عَنْ بَيْعِ الْغَرَرِ",
          "translationTh": "ท่านรอซูลุลลอฮฺ (ศ็อลลัลลอฮุอะลัยฮิวะซัลลัม) ห้ามการซื้อขายที่มีฆอร็อร",
          "hadithCollection": "เศาะฮีหฺมุสลิม",
          "hadithNumber": 1513,
          "narrator": "อบูฮุร็อยเราะฮฺ (ร.อ.)",
          "grading": "เศาะฮีหฺ",
          "references": [
            {
              "bookTh": "เศาะฮีหฺมุสลิม",
              "bookAr": "صحيح مسلم",
              "author": "อิมามมุสลิม",
              "url": "https://sunnah.com/muslim:1513"
            }
          ]
        },
        {
          "type": "hadith",
          "textAr": "لَا يَحِلُّ سَلَفٌ وَبَيْعٌ وَلَا شَرْطَانِ فِي بَيْعٍ وَلَا رِبْحُ مَا لَمْ تَضْمَنْ وَلَا بَيْعُ مَا لَيْسَ عِنْدَكَ",
          "translationTh": "ไม่อนุญาตให้รวมการกู้ยืม (สะลัฟ) กับการซื้อขาย ไม่อนุญาตสองเงื่อนไขในการซื้อขายเดียว ไม่อนุญาตกำไรจากสิ่งที่ยังไม่ได้ค้ำประกัน และไม่อนุญาตขายสิ่งที่ไม่อยู่กับเจ้า",
          "hadithCollection": "สุนัน อบี ดาวูด",
          "hadithNumber": 3504,
          "narrator": "อับดุลลอฮฺ อิบนุ อัมร์ (ร.อ.)",
          "grading": "หะซัน เศาะฮีหฺ",
          "references": [
            {
              "bookTh": "สุนัน อบี ดาวูด",
              "bookAr": "سنن أبي داود",
              "author": "อบู ดาวูด",
              "url": "https://sunnah.com/abudawud:3504"
            }
          ]
        },
        {
          "type": "quran",
          "textAr": "يَا أَيُّهَا الَّذِينَ آمَنُوا لَا تَأْكُلُوا الرِّبَا أَضْعَافًا مُّضَاعَفَةً",
          "translationTh": "โอ้บรรดาผู้ศรัทธาเอ๋ย! อย่ากินดอกเบี้ย (ริบา) ทบทวีคูณ",
          "surah": "อาลิอิมรอน",
          "ayah": "3:130",
          "references": [
            {
              "bookTh": "อัลกุรอาน สูเราะฮฺอาลิอิมรอน อายะฮฺที่ 130",
              "bookAr": "سورة آل عمران آية 130",
              "url": "https://quran.com/3/130"
            }
          ]
        },
        {
          "type": "scholarly_reasoning",
          "translationTh": "กฎฟิกฮ์: 'การกู้ยืมทุกรูปแบบที่มีผลประโยชน์ (ให้ผู้ให้กู้) ถือเป็นริบา' (كل قرض جر نفعاً فهو ربا) โบรกเกอร์ให้ยืมเงินเพื่อเทรดโดยเก็บค่า swap/rollover ซึ่งเป็นดอกเบี้ยแฝง นอกจากนี้ หะดีษ 'ลา ยะฮิลลุ สะลัฟ วะบัยอ์' ห้ามการรวมกู้ยืมกับการซื้อขายในสัญญาเดียว ซึ่ง margin forex ทำอยู่โดยตรง",
          "reasoning": "كل قرض جر نفعاً فهو ربا + لا يحل سلف وبيع",
          "references": [
            {
              "bookTh": "สารานุกรมฟิกฮ์ อัด-ดุร็อร",
              "bookAr": "الموسوعة الفقهية - الدرر السنية",
              "url": "https://dorar.net/feqhia/10345"
            }
          ]
        }
      ],
      "explanation": "สภาฟิกฮ์และนักวิชาการส่วนใหญ่ห้ามฟอเร็กซ์ออนไลน์แบบ margin ด้วยเหตุผล:\n\n1. **ริบาจาก Swap/Rollover**: ค่าธรรมเนียมค้างคืน (overnight fee) เป็นดอกเบี้ยจากการยืมเงิน ซึ่งเป็นริบาที่ชัดเจน\n\n2. **ริบาจาก Leverage**: เงินที่โบรกเกอร์ให้ยืม (เช่น 1:100) เป็นการกู้ยืมที่มีผลประโยชน์ให้ผู้ให้กู้ เข้ากฎ 'กู้ยืมที่มีผลประโยชน์คือริบา'\n\n3. **ไม่มีการส่งมอบจริง (التقابض)**: ฟอเร็กซ์ออนไลน์ไม่มีการส่งมอบสกุลเงินจริง ผู้เทรดไม่เคยถือสกุลเงินต่างประเทศจริง เป็นเพียงตัวเลขในระบบ ขัดเงื่อนไข 'มือต่อมือ' ในหะดีษ\n\n4. **Islamic Account / Swap-free**: บัญชีที่อ้างว่า swap-free มักแค่เปลี่ยนชื่อค่าธรรมเนียม (เป็น administration fee) แต่สาระสำคัญเหมือนเดิม ซึ่งเป็นฮีละฮฺ (อุบาย) ที่ไม่เปลี่ยนหุก่ม\n\n5. **ส่วนใหญ่ของนักเทรดขาดทุน** (สถิติ 70-90%) แสดงว่ากำไรฝ่ายหนึ่งมาจากขาดทุนอีกฝ่าย ลักษณะนี้ใกล้เคียงมัยซิร (การพนัน)"
    }
  ],
  "relatedFatwaIds": ["gold-trading-spot-vs-deferred", "margin-trading", "riba-bank-interest", "derivatives-ruling", "gharar-contracts", "money-exchange"],
  "lastUpdated": "2026-03-14"
}