{
  "id": "funeral-condolence-period",
  "sourceUrl": "https://islamweb.net/ar/fatwa/6744/",
  "titleTh": "หุก่มระยะเวลาการแสดงความเสียใจ (อะซาอฺ) สามวัน",
  "titleAr": "حكم مدة العزاء ثلاثة أيام",
  "categoryId": "general",
  "subcategoryId": "adab",
  "summaryTh": "นักวิชาการส่วนใหญ่มีทัศนะว่าอนุญาตให้แสดงความเสียใจ (ตะอฺซียะฮฺ) ได้สามวัน ห้ามไว้ทุกข์เกินสามวันยกเว้นภรรยาที่สามีเสียชีวิต มีข้อถกเถียงเกี่ยวกับการรวมกลุ่มกันรับแขกที่บ้านผู้เสียชีวิต",
  "introduction": "การแสดงความเสียใจ (التعزية) เป็นซุนนะฮฺที่สนับสนุนให้ทำเพื่อปลอบใจครอบครัวผู้เสียชีวิต มีคำถามเกี่ยวกับระยะเวลาและรูปแบบที่ถูกต้องตามชะรีอะฮฺ",
  "keywords": [
    "อะซาอฺ",
    "แสดงความเสียใจ",
    "ไว้ทุกข์",
    "สามวัน",
    "عزاء",
    "تعزية",
    "الإحداد",
    "ثلاثة أيام"
  ],
  "opinions": [
    {
      "id": "condolence-three-days",
      "position": "ห้ามไว้ทุกข์เกินสามวัน ยกเว้นภรรยาที่สามีเสียชีวิต (สี่เดือนสิบวัน)",
      "positionAr": "يحرم الإحداد فوق ثلاثة أيام إلا على زوجها أربعة أشهر وعشراً",
      "scholars": [
        {
          "name": "มัซฮับหะนะฟียฺ",
          "nameAr": "المذهب الحنفي",
          "era": "มัซฮับ",
          "madhab": "hanafi",
          "type": "madhab"
        },
        {
          "name": "มัซฮับมาลิกียฺ",
          "nameAr": "المذهب المالكي",
          "era": "มัซฮับ",
          "madhab": "maliki",
          "type": "madhab"
        },
        {
          "name": "มัซฮับชาฟิอียฺ",
          "nameAr": "المذهب الشافعي",
          "era": "มัซฮับ",
          "madhab": "shafii",
          "type": "madhab"
        },
        {
          "name": "มัซฮับฮันบะลียฺ",
          "nameAr": "المذهب الحنبلي",
          "era": "มัซฮับ",
          "madhab": "hanbali",
          "type": "madhab"
        }
      ],
      "evidence": [
        {
          "type": "hadith",
          "textAr": "لَا يَحِلُّ لِامْرَأَةٍ تُؤْمِنُ بِاللَّهِ وَالْيَوْمِ الآخِرِ أَنْ تُحِدَّ عَلَى مَيِّتٍ فَوْقَ ثَلَاثٍ إِلَّا عَلَى زَوْجٍ أَرْبَعَةَ أَشْهُرٍ وَعَشْرًا",
          "translationTh": "ไม่อนุญาตสำหรับสตรีที่ศรัทธาต่ออัลลอฮฺและวันอาคิเราะฮฺที่จะไว้ทุกข์ต่อผู้เสียชีวิตเกินสามวัน ยกเว้นต่อสามี คือสี่เดือนกับสิบวัน",
          "hadithCollection": "เศาะฮีหฺอัล-บุคอรีย์",
          "hadithNumber": 1283,
          "narrator": "อุมมุ หะบีบะฮฺ (ร.อ.)",
          "grading": "เศาะฮีหฺ",
          "references": [
            {
              "bookTh": "เศาะฮีหฺอัล-บุคอรีย์",
              "bookAr": "صحيح البخاري",
              "author": "อิมามอัล-บุคอรีย์",
              "url": "https://sunnah.com/bukhari:1283"
            }
          ]
        }
      ],
      "strength": "อิจมาอฺ (เห็นพ้อง) ของนักวิชาการทั้งสี่มัซฮับ"
    },
    {
      "id": "condolence-taziyah-timing",
      "position": "การตะอฺซียะฮฺ (แสดงความเสียใจ) อนุญาตได้แม้หลังสามวัน แต่ไว้ทุกข์ (อิห์ดาด) ต้องไม่เกินสามวัน",
      "positionAr": "التعزية تجوز بعد ثلاثة أيام لكن الإحداد لا يزيد عن ثلاث",
      "scholars": [
        {
          "name": "มัซฮับชาฟิอียฺ",
          "nameAr": "المذهب الشافعي",
          "era": "มัซฮับ",
          "madhab": "shafii",
          "type": "madhab"
        },
        {
          "name": "ชัยคฺ อิบนุ อุษัยมีน",
          "nameAr": "الشيخ ابن عثيمين",
          "era": "1347-1421 ฮ.ศ.",
          "madhab": "hanbali",
          "type": "contemporary_scholar"
        }
      ],
      "evidence": [
        {
          "type": "reasoning",
          "textTh": "ต้องแยกระหว่างสองเรื่อง: (1) อิห์ดาด (الإحداد) คือการไว้ทุกข์ ซึ่งห้ามเกินสามวัน (2) ตะอฺซียะฮฺ (التعزية) คือการแสดงความเสียใจ ซึ่งเป็นซุนนะฮฺและทำได้ทุกเวลา ไม่จำกัดสามวัน"
        }
      ],
      "strength": "ทัศนะที่แยกแยะระหว่างสองประเด็นอย่างชัดเจน"
    }
  ],
  "rulingNotes": "สิ่งสำคัญคือต้องแยกระหว่างอิห์ดาด (ไว้ทุกข์) กับตะอฺซียะฮฺ (แสดงความเสียใจ) ไว้ทุกข์ห้ามเกินสามวัน ยกเว้นภรรยาผู้เสียชีวิต แต่การแสดงความเสียใจทำได้ทุกเวลา ประเพณีจัดงานรับแขกเจ็ดวันหรือสี่สิบวันไม่มีหลักฐานจากซุนนะฮฺ"
}