{
  "id": "insurance-takaful",
  "sourceUrl": "https://dorar.net/feqhia/4356",
  "titleTh": "ประกันภัยแบบตะกาฟุลและประกันทั่วไป",
  "titleAr": "الفرق بين التأمين التقليدي والتكافل",
  "categoryId": "muamalat",
  "subcategoryId": "muamalat-buyu",
  "summaryTh": "ประกันภัยทั่วไปฮะรอมตามสภาฟิกฮ์ส่วนใหญ่เพราะมี gharar ริบา และการพนัน ส่วนตะกาฟุลอนุญาตเพราะเป็นการแบ่งปันความเสี่ยงร่วมกัน บางนักวิชาการอนุญาตประกันทั่วไปในกรณีจำเป็น",
  "introduction": "ประกันภัยทั่วไป (التأمين التجاري) คือสัญญาที่ผู้เอาประกันจ่ายเบี้ยประกันให้บริษัทประกัน และบริษัทชดใช้ค่าเสียหายเมื่อเกิดเหตุ ตะกาฟุล (التكافل) คือประกันภัยอิสลามที่ผู้เอาประกันร่วมกันบริจาคเงินเข้ากองทุน เพื่อช่วยเหลือผู้ที่เกิดความเสียหาย",
  "keywords": [
    "ประกันภัย",
    "ตะกาฟุล",
    "เบี้ยประกัน",
    "การประกันชีวิต",
    "التأمين",
    "التكافل",
    "التأمين الإسلامي",
    "التأمين التجاري"
  ],
  "opinions": [
    {
      "id": "conventional-insurance-haram",
      "position": "ประกันภัยทั่วไปฮะรอม ตะกาฟุลโอเค (ฮัยอะฮฺ ไฟซอล และสภาฟิกฮ์ส่วนใหญ่)",
      "positionAr": "التأمين التجاري محرم والتكافل جائز",
      "scholars": [
        {
          "name": "สภาฟิกฮ์อิสลามนานาชาติ (OIC)",
          "nameAr": "مجمع الفقه الإسلامي الدولي",
          "era": "มติที่ 9 ปี 1985",
          "madhab": "consensus",
          "type": "fiqh_council"
        },
        {
          "name": "สภาอุละมาอ์อาวุโสแห่งซาอุดีอาระเบีย",
          "nameAr": "هيئة كبار العلماء",
          "era": "มติที่ 51 ปี 1977",
          "madhab": "hanbali",
          "type": "fiqh_council"
        },
        {
          "name": "อิบนุ บาซ",
          "nameAr": "ابن باز",
          "era": "1330-1420 ฮ.ศ.",
          "madhab": "hanbali",
          "type": "contemporary_scholar"
        },
        {
          "name": "อิบนุ อุษัยมีน",
          "nameAr": "ابن عثيمين",
          "era": "1347-1421 ฮ.ศ.",
          "madhab": "hanbali",
          "type": "contemporary_scholar"
        }
      ],
      "evidence": [
        {
          "type": "quran",
          "textAr": "يَا أَيُّهَا الَّذِينَ آمَنُوا لَا تَأْكُلُوا أَمْوَالَكُم بَيْنَكُم بِالْبَاطِلِ",
          "translationTh": "โอ้บรรดาผู้ศรัทธา! จงอย่ากินทรัพย์ของกันและกันโดยมิชอบ",
          "surah": "อัน-นิสาอ์",
          "ayah": "4:29",
          "references": [
            {
              "bookTh": "อัลกุรอาน สูเราะฮฺอัน-นิสาอ์ อายะฮฺที่ 29",
              "bookAr": "سورة النساء آية 29",
              "url": "https://quran.com/4/29"
            }
          ]
        },
        {
          "type": "hadith",
          "textAr": "نَهَى رَسُولُ اللَّهِ صَلَّى اللَّهُ عَلَيْهِ وَسَلَّمَ عَنْ بَيْعِ الْغَرَرِ",
          "translationTh": "ท่านรอซูลุลลอฮฺ (ศ.) ห้ามการซื้อขายที่มีความไม่แน่นอน (gharar)",
          "hadithCollection": "เศาะฮีหฺมุสลิม",
          "hadithNumber": 1513,
          "narrator": "อบู ฮุร็อยเราะฮฺ (ร.อ.)",
          "grading": "เศาะฮีหฺ",
          "references": [
            {
              "bookTh": "เศาะฮีหฺมุสลิม",
              "bookAr": "صحيح مسلم",
              "author": "อิมามมุสลิม",
              "url": "https://sunnah.com/muslim:1513"
            }
          ]
        }
      ],
      "explanation": "สภาฟิกฮ์ OIC มีมติว่าประกันภัยทั่วไปฮะรอมเพราะมีสามปัญหา:\n1. Gharar (ความไม่แน่นอน): ไม่รู้ว่าจะเกิดเหตุหรือไม่ จะได้รับชดใช้เท่าไหร่\n2. Maisir (การพนัน): ผู้เอาประกันอาจได้มากกว่าหรือน้อยกว่าที่จ่ายมาก\n3. Riba: บริษัทประกันนำเบี้ยไปลงทุนในสิ่งที่มีดอกเบี้ย\n\nตะกาฟุลแก้ปัญหาเหล่านี้โดย: เปลี่ยนเบี้ยเป็นการบริจาค (tabarru') สร้างกองทุนร่วมกัน ลงทุนในสิ่งฮะลาลเท่านั้น"
    },
    {
      "id": "conventional-insurance-permissible-necessity",
      "position": "อนุญาตประกันทั่วไปในกรณีจำเป็นหรือบังคับตามกฎหมาย (บางนักวิชาการ)",
      "positionAr": "يجوز التأمين التجاري للضرورة أو الإلزام القانوني",
      "scholars": [
        {
          "name": "ยูสุฟ อัล-เกาะเราะฎอวีย์",
          "nameAr": "يوسف القرضاوي",
          "era": "1345-1443 ฮ.ศ.",
          "madhab": "independent",
          "type": "contemporary_scholar"
        },
        {
          "name": "สภาฟิกฮ์ยุโรป (ECFR)",
          "nameAr": "المجلس الأوروبي للإفتاء والبحوث",
          "era": "ก่อตั้ง 1997",
          "madhab": "independent",
          "type": "fiqh_council"
        }
      ],
      "evidence": [
        {
          "type": "quran",
          "textAr": "فَمَنِ اضْطُرَّ غَيْرَ بَاغٍ وَلَا عَادٍ فَلَا إِثْمَ عَلَيْهِ",
          "translationTh": "แต่ผู้ใดถูกบังคับด้วยความจำเป็น โดยไม่ใช่ผู้ละเมิดและไม่ใช่ผู้เกินขอบเขต ก็ไม่มีบาปแก่เขา",
          "surah": "อัล-บะเกาะเราะฮฺ",
          "ayah": "2:173",
          "references": [
            {
              "bookTh": "อัลกุรอาน สูเราะฮฺอัล-บะเกาะเราะฮฺ อายะฮฺที่ 173",
              "bookAr": "سورة البقرة آية 173",
              "url": "https://quran.com/2/173"
            }
          ]
        }
      ],
      "explanation": "บางนักวิชาการสมัยใหม่อนุญาตประกันทั่วไปในกรณีที่:\n1. กฎหมายบังคับ เช่น ประกันรถยนต์ภาคบังคับ\n2. ไม่มีตะกาฟุลในประเทศนั้น\n3. เป็นความจำเป็นทางชีวิต เช่น ประกันสุขภาพเพื่อเข้าถึงการรักษาพยาบาล\n\nโดยใช้หลักฎอรูเราะฮฺ (ความจำเป็น) แต่ต้องจำกัดเฉพาะที่จำเป็นจริงๆ"
    },
    {
      "id": "insurance-all-haram-zahiri",
      "position": "ห้ามทั้งหมด ทั้งประกันทั่วไปและตะกาฟุล (ทัศนะเข้มงวด)",
      "positionAr": "كل أنواع التأمين محرمة",
      "scholars": [
        {
          "name": "บางนักวิชาการซาลาฟีย์เข้มงวด",
          "nameAr": "بعض العلماء السلفيين المتشددين",
          "era": "ศตวรรษที่ 20-21",
          "madhab": "hanbali",
          "type": "contemporary_scholar"
        }
      ],
      "evidence": [
        {
          "type": "hadith",
          "textAr": "نَهَى رَسُولُ اللَّهِ صَلَّى اللَّهُ عَلَيْهِ وَسَلَّمَ عَنْ بَيْعِ الْغَرَرِ",
          "translationTh": "ท่านรอซูลุลลอฮฺ (ศ.) ห้ามการซื้อขายที่มีความไม่แน่นอน",
          "hadithCollection": "เศาะฮีหฺมุสลิม",
          "hadithNumber": 1513,
          "narrator": "อบู ฮุร็อยเราะฮฺ (ร.อ.)",
          "grading": "เศาะฮีหฺ",
          "references": [
            {
              "bookTh": "เศาะฮีหฺมุสลิม",
              "bookAr": "صحيح مسلم",
              "author": "อิมามมุสลิม",
              "url": "https://sunnah.com/muslim:1513"
            }
          ]
        }
      ],
      "explanation": "ทัศนะเข้มงวดนี้เห็นว่าตะกาฟุลก็ยังมีปัญหา gharar เพราะยังไม่รู้ว่าจะเกิดเหตุหรือไม่ จะได้รับชดใช้เท่าไหร่ ดังนั้นจึงห้ามทั้งหมด ทัศนะนี้เป็นส่วนน้อยมากในโลกอิสลาม"
    }
  ],
  "relatedFatwaIds": ["bank-savings-account", "peer-to-peer-lending", "work-for-riba-bank"],
  "lastUpdated": "2026-03-10"
}
