{
  "id": "seeking-knowledge-obligation",
  "sourceUrl": "https://dorar.net/feqhia/508",
  "titleTh": "การแสวงหาความรู้: วาญิบหรือฟัรฎ์กิฟายะฮฺ",
  "titleAr": "طلب العلم فريضة",
  "categoryId": "general",
  "subcategoryId": "education",
  "summaryTh": "ญุมฮูรเห็นว่าความรู้พื้นฐานทางศาสนาเป็นฟัรฎ์อัยน์สำหรับทุกคน ส่วนความรู้ขั้นสูงเป็นฟัรฎ์กิฟายะฮฺ บางทัศนะเห็นว่าทุกความรู้ที่เป็นประโยชน์มีส่วนหนึ่งที่เป็นวาญิบ",
  "introduction": "การแสวงหาความรู้ (طلب العلم) ได้รับการส่งเสริมอย่างสูงในอิสลาม แต่นักวิชาการแตกต่างกันในการจำแนกระดับวาญิบ โดยเฉพาะว่าความรู้ประเภทใดเป็นฟัรฎ์อัยน์ (วาญิบสำหรับทุกคน) และประเภทใดเป็นฟัรฎ์กิฟายะฮฺ (วาญิบสำหรับบางคนในชุมชน)",
  "keywords": ["ความรู้", "ฟัรฎ์", "วาญิบ", "กิฟายะฮฺ", "อัยน์", "العلم", "فرض", "طلب العلم"],
  "opinions": [
    {
      "id": "op1",
      "position": "ญุมฮูร: ความรู้พื้นฐานวาญิบสำหรับทุกคน (ฟัรฎ์อัยน์) ส่วนที่เหลือฟัรฎ์กิฟายะฮฺ",
      "positionAr": "طلب العلم فرض عين في أصوله وفرض كفاية في تفاصيله",
      "scholars": [
        {
          "name": "อิมามอัล-ฆอซาลีย์",
          "nameAr": "الإمام الغزالي",
          "era": "450-505 ฮ.ศ.",
          "madhab": "shafii",
          "type": "classical_scholar"
        },
        {
          "name": "อิมามอัน-นะวะวีย์",
          "nameAr": "الإمام النووي",
          "era": "631-676 ฮ.ศ.",
          "madhab": "shafii",
          "type": "classical_scholar"
        },
        {
          "name": "อิบนุ กุดามะฮฺ",
          "nameAr": "ابن قدامة",
          "era": "541-620 ฮ.ศ.",
          "madhab": "hanbali",
          "type": "classical_scholar"
        }
      ],
      "evidence": [
        {
          "type": "hadith",
          "textAr": "طَلَبُ الْعِلْمِ فَرِيضَةٌ عَلَى كُلِّ مُسْلِمٍ",
          "translationTh": "การแสวงหาความรู้เป็นฟัรฎ์สำหรับทุกมุสลิม",
          "hadithCollection": "Ibn Majah",
          "hadithNumber": 224,
          "narrator": "อนัส บิน มาลิก",
          "grading": "เศาะหีหฺ (อัล-อัลบานีย์)",
          "references": [
            {
              "bookTh": "สุนัน อิบนุ มาญะฮฺ",
              "bookAr": "سنن ابن ماجه",
              "author": "อิบนุ มาญะฮฺ",
              "url": "https://sunnah.com/ibnmajah:224"
            }
          ]
        }
      ],
      "explanation": "อัล-ฆอซาลีย์อธิบายในอิหฺยาอ์ อุลูมุดดีนว่าความรู้ที่วาญิบสำหรับทุกคนคือสิ่งที่จำเป็นสำหรับการปฏิบัติอิบาดะฮฺและมุอามะลาฮฺที่บุคคลนั้นต้องทำ ส่วนความรู้ขั้นสูงเช่นอุศูลุลฟิกฮฺและตัฟซีรเชิงลึกเป็นฟัรฎ์กิฟายะฮฺ"
    },
    {
      "id": "op2",
      "position": "บางทัศนะ: ทุกความรู้ที่เป็นประโยชน์มีความจำเป็นในระดับหนึ่ง รวมถึงความรู้ทางโลก",
      "positionAr": "كل علم نافع فيه درجة من الوجوب بحسب الحاجة الفردية والجماعية",
      "scholars": [
        {
          "name": "อิบนุ ตัยมียะฮฺ",
          "nameAr": "ابن تيمية",
          "era": "661-728 ฮ.ศ.",
          "madhab": "hanbali",
          "type": "classical_scholar"
        },
        {
          "name": "ยูสุฟ อัล-กอรฎอวีย์",
          "nameAr": "يوسف القرضاوي",
          "era": "1345-1443 ฮ.ศ.",
          "madhab": "independent",
          "type": "contemporary_scholar"
        }
      ],
      "evidence": [
        {
          "type": "quran",
          "textAr": "قُلْ هَلْ يَسْتَوِي الَّذِينَ يَعْلَمُونَ وَالَّذِينَ لَا يَعْلَمُونَ",
          "translationTh": "จงกล่าวว่า 'บรรดาผู้รู้และผู้ที่ไม่รู้เท่าเทียมกันหรือ?'",
          "references": [
            {
              "bookTh": "อัล-กุรอาน ซูเราะฮฺ อัซ-ซุมัร อายะฮฺ 9",
              "bookAr": "القرآن الكريم سورة الزمر آية 9",
              "author": "อัลลอฮฺ",
              "url": "https://quran.com/39/9"
            }
          ]
        }
      ],
      "explanation": "อิบนุ ตัยมียะฮฺขยายแนวคิดว่าความรู้ที่ชุมชนมุสลิมต้องการเพื่อเป็นอิสระและเข้มแข็งก็มีลักษณะเป็นฟัรฎ์กิฟายะฮฺ รวมถึงความรู้ทางวิทยาศาสตร์ การแพทย์ และวิศวกรรม"
    }
  ],
  "relatedFatwaIds": ["social-media-time", "hadith-weak-deeds"],
  "lastUpdated": "2026-03-10"
}
