{
  "id": "zakah-salary",
  "sourceUrl": "https://islamweb.net/ar/fatwa/26084/",
  "titleTh": "ซะกาตเงินเดือน",
  "titleAr": "زكاة الراتب الشهري",
  "categoryId": "zakah",
  "subcategoryId": "zakah-mal",
  "summaryTh": "นักวิชาการมีทัศนะต่างกันเกี่ยวกับวิธีคำนวณซะกาตเงินเดือน ทัศนะหลักเห็นว่าให้รวมเงินเดือนกับเงินออมทั้งหมดแล้วจ่ายซะกาตเมื่อครบรอบปี ส่วนทัศนะร่วมสมัยบางส่วนอนุญาตให้จ่ายซะกาตเงินเดือนทุกเดือนได้",
  "introduction": "เงินเดือนเป็นรายได้ที่เกิดขึ้นซ้ำทุกเดือน ทำให้เกิดคำถามว่าต้องคำนวณซะกาตอย่างไร จะนับรอบปีจากเดือนแรกที่รับเงินเดือน หรือจะรวมเงินเดือนทั้งปีแล้วจ่ายพร้อมกัน นักวิชาการได้วินิจฉัยประเด็นนี้ตามหลักฟิกฮ์และมัซฮับต่างๆ",
  "keywords": [
    "ซะกาต",
    "เงินเดือน",
    "รายได้",
    "ฮาวลฺ",
    "رواتب",
    "زكاة الراتب",
    "الحول"
  ],
  "opinions": [
    {
      "id": "year-end-calculation",
      "position": "รวมเงินเดือนทั้งปีแล้วคำนวณซะกาตเมื่อครบรอบปีพร้อมกับเงินออมที่มีอยู่ (ทัศนะส่วนใหญ่)",
      "positionAr": "ضم الراتب إلى بقية المال وإخراج زكاته عند حولان الحول",
      "scholars": [
        {
          "name": "อิบนุ บาซ",
          "nameAr": "ابن باز",
          "era": "1330-1420 ฮ.ศ.",
          "madhab": "hanbali",
          "type": "contemporary_scholar"
        },
        {
          "name": "อิบนุ อุษัยมีน",
          "nameAr": "ابن عثيمين",
          "era": "1347-1421 ฮ.ศ.",
          "madhab": "hanbali",
          "type": "contemporary_scholar"
        },
        {
          "name": "คณะกรรมการถาวรเพื่อการวิจัยและฟัตวา",
          "nameAr": "اللجنة الدائمة للبحوث العلمية والإفتاء",
          "era": "ก่อตั้ง 1391 ฮ.ศ.",
          "madhab": "hanbali",
          "type": "fiqh_council"
        }
      ],
      "evidence": [
        {
          "type": "hadith",
          "textAr": "لَيْسَ فِيمَا دُونَ خَمْسِ أَوَاقٍ صَدَقَةٌ",
          "translationTh": "ไม่มีซะกาตสำหรับทรัพย์ที่ต่ำกว่าห้าอูกียะฮฺ",
          "hadithCollection": "เศาะฮีหฺบุคอรี",
          "hadithNumber": 1405,
          "narrator": "อะบู สะอีด อัล-คุดรี (ร.อ.)",
          "grading": "เศาะฮีหฺ",
          "references": [
            {
              "bookTh": "เศาะฮีหฺบุคอรี",
              "bookAr": "صحيح البخاري",
              "author": "อิมามบุคอรี",
              "url": "https://sunnah.com/bukhari:1405"
            }
          ]
        },
        {
          "type": "quran",
          "surahNumber": 9,
          "surahName": "อัต-เตาบะฮฺ",
          "surahNameAr": "التوبة",
          "ayahNumber": 103,
          "textAr": "خُذْ مِنْ أَمْوَالِهِمْ صَدَقَةً تُطَهِّرُهُمْ وَتُزَكِّيهِم بِهَا",
          "translationTh": "จงเก็บซะกาตจากทรัพย์สินของพวกเขา เพื่อชำระและทำให้พวกเขาบริสุทธิ์ด้วยมัน",
          "references": [
            {
              "bookTh": "อัลกุรอาน สูเราะฮฺอัต-เตาบะฮฺ อายะฮฺที่ 103",
              "bookAr": "سورة التوبة: ١٠٣",
              "url": "https://quran.com/9/103"
            }
          ]
        }
      ],
      "explanation": "ทัศนะนี้ถือว่าเงินเดือนที่ได้รับแต่ละเดือนจะถูกรวมเข้ากับเงินออมที่มีอยู่แล้ว เมื่อถึงรอบปีของเงินออมหลัก ให้นับเงินทั้งหมดที่มีในขณะนั้น (รวมเงินเดือนที่ยังเหลืออยู่) แล้วจ่ายซะกาต 2.5% หากถึงนิศอบ วิธีนี้ง่ายและสะดวก ไม่ต้องติดตามเฮาลฺแยกสำหรับแต่ละเดือน"
    },
    {
      "id": "monthly-calculation",
      "position": "จ่ายซะกาตเงินเดือนทุกเดือนได้ โดยประมาณการค่าใช้จ่ายและจ่ายซะกาตจากส่วนที่คาดว่าจะเหลือ (ทัศนะร่วมสมัยบางส่วน)",
      "positionAr": "جواز إخراج زكاة الراتب شهرياً تيسيراً على الناس",
      "scholars": [
        {
          "name": "ยูสุฟ อัล-เกาะเราะฎอวี",
          "nameAr": "يوسف القرضاوي",
          "era": "1345-1443 ฮ.ศ.",
          "madhab": "independent",
          "type": "contemporary_scholar"
        },
        {
          "name": "อับดุลลอฮฺ อิบนุ มานิอฺ",
          "nameAr": "عبد الله بن منيع",
          "era": "ร่วมสมัย",
          "madhab": "hanbali",
          "type": "contemporary_scholar"
        }
      ],
      "evidence": [
        {
          "type": "quran",
          "surahNumber": 2,
          "surahName": "อัล-บะเกาะเราะฮฺ",
          "surahNameAr": "البقرة",
          "ayahNumber": 267,
          "textAr": "يَا أَيُّهَا الَّذِينَ آمَنُوا أَنفِقُوا مِن طَيِّبَاتِ مَا كَسَبْتُمْ",
          "translationTh": "โอ้บรรดาผู้ศรัทธาทั้งหลาย จงบริจาคจากสิ่งดีๆ ที่พวกเจ้าหาได้มา",
          "references": [
            {
              "bookTh": "อัลกุรอาน สูเราะฮฺอัล-บะเกาะเราะฮฺ อายะฮฺที่ 267",
              "bookAr": "سورة البقرة: ٢٦٧",
              "url": "https://quran.com/2/267"
            }
          ]
        }
      ],
      "explanation": "อัล-เกาะเราะฎอวีเห็นว่าเงินเดือนเป็นรายได้ที่หมุนเวียน ควรจ่ายซะกาตจากรายได้ทันทีที่ได้รับโดยอนุโลม โดยอาศัยหลักการกิยาสกับซะกาตพืชผลที่จ่าย ณ เวลาเก็บเกี่ยว ไม่ต้องรอครบรอบปี ทัศนะนี้เป็นการเปิดกว้างสำหรับผู้ที่สะดวกจ่ายซะกาตทุกเดือน แต่ไม่ใช่ทัศนะที่ถูกต้องกว่าหากเทียบกับทัศนะส่วนใหญ่"
    }
  ],
  "relatedFatwaIds": ["zakah-saved-money", "zakah-paper-money"],
  "lastUpdated": "2026-03-10"
}
